alyx_connector-2.1.45.dist-info/METADATA
alyx_connector-2.1.45.dist-info/WHEEL
alyx_connector-2.1.45.dist-info/entry_points.txt
alyx_connector-2.1.45.dist-info/licenses/LICENSE
alyx_connector/.gitignore
alyx_connector/__init__.py
alyx_connector/connector/__init__.py
alyx_connector/connector/core.py
alyx_connector/files/__init__.py
alyx_connector/files/parsing/__init__.py
alyx_connector/files/parsing/expressions.py
alyx_connector/files/parsing/files.py
alyx_connector/files/parsing/rulesets.py
alyx_connector/files/registration/__init__.py
alyx_connector/files/registration/files.py
alyx_connector/files/registration/manage.py
alyx_connector/files/registration/rules.json
alyx_connector/files/registration/rules_config.py
alyx_connector/files/registration/utils.py
alyx_connector/files/transfers/transfers.py
alyx_connector/nwb/__init__.py
alyx_connector/nwb/create.py
alyx_connector/utils/__init__.py
alyx_connector/utils/configuration.py
alyx_connector/utils/logging.py
alyx_connector/utils/render_classes.py
alyx_connector/utils/types.py
alyx_connector/web/__init__.py
alyx_connector/web/api.py
alyx_connector/web/clients.py
alyx_connector/web/tools/creation.py
alyx_connector/web/urls.py
alyx_connector-2.1.45.dist-info/RECORD
