Metadata-Version: 2.1
Name: alyx-connector
Version: 2.1.45
Summary: Alyx Connector, based on the Open Neurophysiology Environment
Author-Email: =?utf-8?q?Timoth=C3=A9_Jost-Mousseau?= <timothe.jost-mousseau@pasteur.fr>
Maintainer-Email: =?utf-8?q?Timoth=C3=A9_Jost-Mousseau?= <timothe.jost-mousseau@pasteur.fr>
License: MIT
Project-URL: homepage, https://gitlab.pasteur.fr/haisslab/data-management/ONE
Project-URL: repository, https://gitlab.pasteur.fr/haisslab/data-management/ONE
Project-URL: documentation, https://gitlab.pasteur.fr/haisslab/data-management/ONE
Requires-Python: <3.13,>=3.12
Requires-Dist: iblutil>=1.7.0
Requires-Dist: natsort>=8.4.0
Requires-Dist: numpy>=1.25.2
Requires-Dist: packaging>=23.2
Requires-Dist: pandas>=2.1.4
Requires-Dist: PyYAML>=6.0.1
Requires-Dist: Requests>=2.31.0
Requires-Dist: pint
Requires-Dist: rich
Requires-Dist: openapi3-parser>=1.1.19
Requires-Dist: pynwb>=3.1.2
Provides-Extra: docs
Requires-Dist: mkdocs-material>=9.6.12; extra == "docs"
Provides-Extra: tests
Requires-Dist: pytest-cov>=6.2.1; extra == "tests"
Requires-Dist: responses>=0.25.7; extra == "tests"
